django_loggers_test/__init__.py
django_loggers_test/django_loggers_test.py
django_loggers_test/version.py
django_loggers_test-1.0.3.dist-info/METADATA
django_loggers_test-1.0.3.dist-info/WHEEL
django_loggers_test-1.0.3.dist-info/RECORD
