Metadata-Version: 2.1
Name: django_loggers_test
Version: 1.0.3
Summary: A simple tester of Django's loggers' configuration
Project-URL: Homepage, https://github.com/vsego/django_loggers_test
Project-URL: Bug Tracker, https://github.com/vsego/django_loggers_test/issues
Author-email: Vedran Sego <vsego@vsego.org>
Classifier: License :: OSI Approved :: MIT License
Classifier: Operating System :: OS Independent
Classifier: Programming Language :: Python :: 3
Requires-Python: >=3.5
